<collection xmlns="http://exist.sourceforge.net/NS/exist" name="/db/apps/iati/codes" owner="admin" group="dba" mode="755" created="2012-06-23T15:24:35+01:00" version="1">
    <acl entries="0" version="1"/>
    <resource type="XMLResource" name="ActivityDateType-0.9-en.xml" owner="admin" group="dba" mode="644" created="2012-06-23T15:24:35+01:00" modified="2012-06-23T15:24:35+01:00" filename="ActivityDateType-0.9-en.xml" mimetype="application/xml">
        <acl entries="0" version="1"/>
    </resource>
    <resource type="XMLResource" name="ActivityDateType-1.0-en.xml" owner="admin" group="dba" mode="644" created="2012-06-23T15:24:35+01:00" modified="2012-06-23T15:24:35+01:00" filename="ActivityDateType-1.0-en.xml" mimetype="application/xml">
        <acl entries="0" version="1"/>
    </resource>
    <resource type="XMLResource" name="ActivityDateType-1.0-es.xml" owner="admin" group="dba" mode="644" created="2012-06-23T15:24:35+01:00" modified="2012-06-23T15:24:35+01:00" filename="ActivityDateType-1.0-es.xml" mimetype="application/xml">
        <acl entries="0" version="1"/>
    </resource>
    <resource type="XMLResource" name="ActivityStatus-1.0-en.xml" owner="admin" group="dba" mode="644" created="2012-06-23T15:24:35+01:00" modified="2012-06-23T15:24:35+01:00" filename="ActivityStatus-1.0-en.xml" mimetype="application/xml">
        <acl entries="0" version="1"/>
    </resource>
    <resource type="XMLResource" name="AidType-1.0-en.xml" owner="admin" group="dba" mode="644" created="2012-06-23T15:24:35+01:00" modified="2012-06-23T15:24:35+01:00" filename="AidType-1.0-en.xml" mimetype="application/xml">
        <acl entries="0" version="1"/>
    </resource>
    <resource type="XMLResource" name="BudgetType-1.0-en.xml" owner="admin" group="dba" mode="644" created="2012-06-23T15:24:35+01:00" modified="2012-06-23T15:24:35+01:00" filename="BudgetType-1.0-en.xml" mimetype="application/xml">
        <acl entries="0" version="1"/>
    </resource>
    <resource type="XMLResource" name="CollaborationType-1.0-en.xml" owner="admin" group="dba" mode="644" created="2012-06-23T15:24:36+01:00" modified="2012-06-23T15:24:36+01:00" filename="CollaborationType-1.0-en.xml" mimetype="application/xml">
        <acl entries="0" version="1"/>
    </resource>
    <resource type="XMLResource" name="ConditionType-1.0-en.xml" owner="admin" group="dba" mode="644" created="2012-06-23T15:24:36+01:00" modified="2012-06-23T15:24:36+01:00" filename="ConditionType-1.0-en.xml" mimetype="application/xml">
        <acl entries="0" version="1"/>
    </resource>
    <resource type="XMLResource" name="Country-1.0-en.xml" owner="admin" group="dba" mode="644" created="2012-06-23T15:24:36+01:00" modified="2012-06-23T15:24:36+01:00" filename="Country-1.0-en.xml" mimetype="application/xml">
        <acl entries="0" version="1"/>
    </resource>
    <resource type="XMLResource" name="Country-1.01-en.xml" owner="admin" group="dba" mode="644" created="2012-06-23T15:24:36+01:00" modified="2012-06-23T15:24:36+01:00" filename="Country-1.01-en.xml" mimetype="application/xml">
        <acl entries="0" version="1"/>
    </resource>
    <resource type="XMLResource" name="Currency-1.0-en.xml" owner="admin" group="dba" mode="644" created="2012-06-23T15:24:36+01:00" modified="2012-06-23T15:24:36+01:00" filename="Currency-1.0-en.xml" mimetype="application/xml">
        <acl entries="0" version="1"/>
    </resource>
    <resource type="XMLResource" name="DescriptionType-1.0-en.xml" owner="admin" group="dba" mode="644" created="2012-06-23T15:24:36+01:00" modified="2012-06-23T15:24:36+01:00" filename="DescriptionType-1.0-en.xml" mimetype="application/xml">
        <acl entries="0" version="1"/>
    </resource>
    <resource type="XMLResource" name="DisbursementChannel-1.0-en.xml" owner="admin" group="dba" mode="644" created="2012-06-23T15:24:37+01:00" modified="2012-06-23T15:24:37+01:00" filename="DisbursementChannel-1.0-en.xml" mimetype="application/xml">
        <acl entries="0" version="1"/>
    </resource>
    <resource type="XMLResource" name="DocumentCategory-1.0-en.xml" owner="admin" group="dba" mode="644" created="2012-06-23T15:24:37+01:00" modified="2012-06-23T15:24:37+01:00" filename="DocumentCategory-1.0-en.xml" mimetype="application/xml">
        <acl entries="0" version="1"/>
    </resource>
    <resource type="XMLResource" name="FileFormat-1.0-en.xml" owner="admin" group="dba" mode="644" created="2012-06-23T15:24:37+01:00" modified="2012-06-23T15:24:37+01:00" filename="FileFormat-1.0-en.xml" mimetype="application/xml">
        <acl entries="0" version="1"/>
    </resource>
    <resource type="XMLResource" name="FinanceType-1.0-en.xml" owner="admin" group="dba" mode="644" created="2012-06-23T15:24:37+01:00" modified="2012-06-23T15:24:37+01:00" filename="FinanceType-1.0-en.xml" mimetype="application/xml">
        <acl entries="0" version="1"/>
    </resource>
    <resource type="XMLResource" name="FlowType-1.0-en.xml" owner="admin" group="dba" mode="644" created="2012-06-23T15:24:37+01:00" modified="2012-06-23T15:24:37+01:00" filename="FlowType-1.0-en.xml" mimetype="application/xml">
        <acl entries="0" version="1"/>
    </resource>
    <resource type="XMLResource" name="GazetteerAgency-1.0-en.xml" owner="admin" group="dba" mode="644" created="2012-06-23T15:24:37+01:00" modified="2012-06-23T15:24:37+01:00" filename="GazetteerAgency-1.0-en.xml" mimetype="application/xml">
        <acl entries="0" version="1"/>
    </resource>
    <resource type="XMLResource" name="GeographicalPrecision-1.0-en.xml" owner="admin" group="dba" mode="644" created="2012-06-23T15:24:37+01:00" modified="2012-06-23T15:24:37+01:00" filename="GeographicalPrecision-1.0-en.xml" mimetype="application/xml">
        <acl entries="0" version="1"/>
    </resource>
    <resource type="XMLResource" name="IndicatorMeasure-1.0-en.xml" owner="admin" group="dba" mode="644" created="2012-06-23T15:24:37+01:00" modified="2012-06-23T15:24:37+01:00" filename="IndicatorMeasure-1.0-en.xml" mimetype="application/xml">
        <acl entries="0" version="1"/>
    </resource>
    <resource type="XMLResource" name="Language-1.0-en.xml" owner="admin" group="dba" mode="644" created="2012-06-23T15:24:37+01:00" modified="2012-06-23T15:24:37+01:00" filename="Language-1.0-en.xml" mimetype="application/xml">
        <acl entries="0" version="1"/>
    </resource>
    <resource type="XMLResource" name="LocationType-1.0-en.xml" owner="admin" group="dba" mode="644" created="2012-06-23T15:24:38+01:00" modified="2012-06-23T15:24:38+01:00" filename="LocationType-1.0-en.xml" mimetype="application/xml">
        <acl entries="0" version="1"/>
    </resource>
    <resource type="XMLResource" name="OrganisationIdentifier-1.0-en.xml" owner="admin" group="dba" mode="644" created="2012-06-23T15:24:38+01:00" modified="2012-06-23T15:24:38+01:00" filename="OrganisationIdentifier-1.0-en.xml" mimetype="application/xml">
        <acl entries="0" version="1"/>
    </resource>
    <resource type="XMLResource" name="OrganisationRole-1.0-en.xml" owner="admin" group="dba" mode="644" created="2012-06-23T15:24:38+01:00" modified="2012-06-23T15:24:38+01:00" filename="OrganisationRole-1.0-en.xml" mimetype="application/xml">
        <acl entries="0" version="1"/>
    </resource>
    <resource type="XMLResource" name="OrganisationType-1.0-en.xml" owner="admin" group="dba" mode="644" created="2012-06-23T15:24:38+01:00" modified="2012-06-23T15:24:38+01:00" filename="OrganisationType-1.0-en.xml" mimetype="application/xml">
        <acl entries="0" version="1"/>
    </resource>
    <resource type="XMLResource" name="PolicyMarker-1.0-en.xml" owner="admin" group="dba" mode="644" created="2012-06-23T15:24:38+01:00" modified="2012-06-23T15:24:38+01:00" filename="PolicyMarker-1.0-en.xml" mimetype="application/xml">
        <acl entries="0" version="1"/>
    </resource>
    <resource type="XMLResource" name="PolicySignificance-1.0-en.xml" owner="admin" group="dba" mode="644" created="2012-06-23T15:24:39+01:00" modified="2012-06-23T15:24:39+01:00" filename="PolicySignificance-1.0-en.xml" mimetype="application/xml">
        <acl entries="0" version="1"/>
    </resource>
    <resource type="XMLResource" name="PublisherType-1.0-en.xml" owner="admin" group="dba" mode="644" created="2012-06-23T15:24:39+01:00" modified="2012-06-23T15:24:39+01:00" filename="PublisherType-1.0-en.xml" mimetype="application/xml">
        <acl entries="0" version="1"/>
    </resource>
    <resource type="XMLResource" name="Region-1.0-en.xml" owner="admin" group="dba" mode="644" created="2012-06-23T15:24:39+01:00" modified="2012-06-23T15:24:39+01:00" filename="Region-1.0-en.xml" mimetype="application/xml">
        <acl entries="0" version="1"/>
    </resource>
    <resource type="XMLResource" name="RelatedActivityType-1.0-en.xml" owner="admin" group="dba" mode="644" created="2012-06-23T15:24:39+01:00" modified="2012-06-23T15:24:39+01:00" filename="RelatedActivityType-1.0-en.xml" mimetype="application/xml">
        <acl entries="0" version="1"/>
    </resource>
    <resource type="XMLResource" name="ResultType-1.0-en.xml" owner="admin" group="dba" mode="644" created="2012-06-23T15:24:39+01:00" modified="2012-06-23T15:24:39+01:00" filename="ResultType-1.0-en.xml" mimetype="application/xml">
        <acl entries="0" version="1"/>
    </resource>
    <resource type="XMLResource" name="Sector-1.0-en.xml" owner="admin" group="dba" mode="644" created="2012-06-23T15:24:39+01:00" modified="2012-06-23T15:24:39+01:00" filename="Sector-1.0-en.xml" mimetype="application/xml">
        <acl entries="0" version="1"/>
    </resource>
    <resource type="XMLResource" name="SectorCategory-1.0-en.xml" owner="admin" group="dba" mode="644" created="2012-06-23T15:24:39+01:00" modified="2012-06-23T15:24:39+01:00" filename="SectorCategory-1.0-en.xml" mimetype="application/xml">
        <acl entries="0" version="1"/>
    </resource>
    <resource type="XMLResource" name="TiedStatus-1.0-en.xml" owner="admin" group="dba" mode="644" created="2012-06-23T15:24:39+01:00" modified="2012-06-23T15:24:39+01:00" filename="TiedStatus-1.0-en.xml" mimetype="application/xml">
        <acl entries="0" version="1"/>
    </resource>
    <resource type="XMLResource" name="TransactionType-1.0-en.xml" owner="admin" group="dba" mode="644" created="2012-06-23T15:24:39+01:00" modified="2012-06-23T15:24:39+01:00" filename="TransactionType-1.0-en.xml" mimetype="application/xml">
        <acl entries="0" version="1"/>
    </resource>
    <resource type="XMLResource" name="ValueType-1.0-en.xml" owner="admin" group="dba" mode="644" created="2012-06-23T15:24:40+01:00" modified="2012-06-23T15:24:40+01:00" filename="ValueType-1.0-en.xml" mimetype="application/xml">
        <acl entries="0" version="1"/>
    </resource>
    <resource type="XMLResource" name="VerificationStatus-1.0-en.xml" owner="admin" group="dba" mode="644" created="2012-06-23T15:24:40+01:00" modified="2012-06-23T15:24:40+01:00" filename="VerificationStatus-1.0-en.xml" mimetype="application/xml">
        <acl entries="0" version="1"/>
    </resource>
    <resource type="XMLResource" name="Vocabulary-1.0-en.xml" owner="admin" group="dba" mode="644" created="2012-06-23T15:24:40+01:00" modified="2012-06-23T15:24:40+01:00" filename="Vocabulary-1.0-en.xml" mimetype="application/xml">
        <acl entries="0" version="1"/>
    </resource>
    <resource type="XMLResource" name="codeindex.xml" owner="admin" group="dba" mode="644" created="2012-06-23T15:24:36+01:00" modified="2012-06-23T15:24:36+01:00" filename="codeindex.xml" mimetype="application/xml">
        <acl entries="0" version="1"/>
    </resource>
    <resource type="XMLResource" name="metadata.xml" owner="admin" group="dba" mode="644" created="2012-06-23T15:24:38+01:00" modified="2012-06-23T15:24:38+01:00" filename="metadata.xml" mimetype="application/xml">
        <acl entries="0" version="1"/>
    </resource>
</collection>